MANIFEST.in
README.md
setup.py
tox.ini
rc_webserver/LICENSE
rc_webserver/__init__.py
rc_webserver/web.py
rc_webserver.egg-info/PKG-INFO
rc_webserver.egg-info/SOURCES.txt
rc_webserver.egg-info/dependency_links.txt
rc_webserver.egg-info/entry_points.txt
rc_webserver.egg-info/requires.txt
rc_webserver.egg-info/top_level.txt
rc_webserver/components/__init__.py
rc_webserver/components/webroot.py
rc_webserver/components/webservice.py
rc_webserver/data/app.config
tests/test_webserver.py